alibabacloud_dts_mcp_server/__init__.py
alibabacloud_dts_mcp_server/server.py
alibabacloud_dts_mcp_server-0.1.4.dist-info/licenses/LICENSE
alibabacloud_dts_mcp_server-0.1.4.dist-info/METADATA
alibabacloud_dts_mcp_server-0.1.4.dist-info/WHEEL
alibabacloud_dts_mcp_server-0.1.4.dist-info/entry_points.txt
alibabacloud_dts_mcp_server-0.1.4.dist-info/top_level.txt
alibabacloud_dts_mcp_server-0.1.4.dist-info/RECORD
