Metadata-Version: 2.4
Name: alibabacloud-dts-mcp-server
Version: 0.1.4
Summary: MCP Server for AlibabaCloud DTS
License-Expression: Apache-2.0
Requires-Python: >=3.13
License-File: LICENSE
Requires-Dist: alibabacloud-dts20200101>=5.8.1
Requires-Dist: httpx>=0.28.1
Requires-Dist: mcp[cli]>=1.8.1
Dynamic: license-file
